masonite_audit/__init__.py
masonite_audit/masonite_audit.py
masonite_audit/config/masonite_audit.py
masonite_audit/migrations/create_audit_logs_table.py
masonite_audit/mixins/__init__.py
masonite_audit/mixins/audit.py
masonite_audit/models/audit_log.py
masonite_audit/observer/__init__.py
masonite_audit/observer/audit_observer.py
masonite_audit/providers/AuditProvider.py
masonite_audit/providers/__init__.py
masonite_audit-0.0.6.dist-info/LICENSE
masonite_audit-0.0.6.dist-info/METADATA
masonite_audit-0.0.6.dist-info/WHEEL
masonite_audit-0.0.6.dist-info/top_level.txt
masonite_audit-0.0.6.dist-info/RECORD
